[
  {
    "answer":"82",
    "description":"Памятник студенческим стройотрядам",
    "history":"Памятник студенческим строительным отрядам перед зданием физического факультета МГУ открыли 14 ноября 2009 года, в год 50-летия стройотрядовского движения. Место для установки памятника выбрано не случайно - первый студенческий стройотряд был создан в 1959 году именно из студентов физфака. Автор памятника - скульптор Александр Иулианнович Рукавишников, представитель целой династии скульпторов Рукавишниковых. Из других его работ можно вспомнить надгробный памятник Владимира Высоцкого на Ваганьково и установленный у храма Христа Спасителя памятник Александру II.",
    "id":"02",
    "lat":"55.698966",
    "lon":"37.527682",
    "name":"Ленинские Горы, МГУ, д.1 корп. 2",
    "quest":"Цифры после слова БАМ"
  },
  {
    "answer":"VOLTYRE",
    "description":"Пожарная машина-памятник на постаменте",
    "id":"03",
    "lat":"55.682133",
    "lon":"37.5492",
    "name":"Ул. Вавилова, д. 68",
    "quest":"Марка шин (семь букв латиницей)"
  },
  {
    "answer":"8 (также принимается ответ 2)",
    "description":"Скульптурные композиции рядом с памятником В. Г. Шухову",
    "history":"Памятник выдающемуся инженеру Владимиру Григорьевичу Шухову открыли на Тургеневской площади 2 декабря 2008 года. Среди его построек наиболее известна \"шуховская башня\" - радиобашня на Шаболовке, сооруженная в 1922 году и долгие годы остававшаяся самым высоким сооружением города. Однако в Москве немало иных произведений Шухова. По его расчётам были созданы конструкции перекрытий в здании ГУМа на Красной площади над перронами Киевского вокзала, перекрытия над залами музея изящных искусств на Волхонке и своды над огромными помещениями городских трамвайных и автобусных парков 1910-1920-х.",
    "id":"04",
    "lat":"55.7661265",
    "lon":"37.6357269",
    "name":"Тургеневская пл.",
    "quest":"Кол-во изображенных людей"
  },
  {
    "answer":"100",
    "description":"БМП на здании",
    "id":"06",
    "lat":"55.737508",
    "lon":"37.579567",
    "name":"Ул. Плющиха, д. 55",
    "quest":"Бортовой номер"
  },
  {
    "answer":"5",
    "description":"Памятная табличка основателю российской рекламы",
    "id":"08",
    "lat":"55.762001",
    "lon":"37.634317",
    "name":"Мясницкая ул., д. 22/2",
    "quest":"Кол-во букв \"Ц\""
  },
  {
    "answer":"подпись",
    "description":"SMall Pub",
    "id":"10",
    "lat":"55.77338",
    "lon":"37.632682",
    "name":"Пр-т Мира, д. 6",
    "quest":"Подпись судьи"
  },
  {
    "answer":"4",
    "description":"Плакат рядом с мостом через р. Сетунь. Х обыкновенный. Единственный вид рода настоящих Х-ов семейства Х-вых",
    "history":"Река Сетунь - самый крупный правый приток Москвы-реки в черте города Москвы. В средние века селения вдоль речной долины были даже объединены в специальную административную единицу - Сетуньский стан. С годами вокруг речной долины выросли многочисленные промышленные зоны и кварталы многоэтажных домов, а сами речные берега покрылись свалками и заросли мелколесьем. В 1998 году создан природный заказник \"Долина реки Сетунь\" - крупнейший по площади в Москве, охватывающий большую часть речной долины. Ведутся работы по очистке реки и благоустройству береговых склонов.",
    "id":"14",
    "lat":"55.7155",
    "lon":"37.4184",
    "name":"Дорогобужская ул.",
    "quest":"Количество русских слов в строчке с латинским названием вида"
  },
  {
    "answer":"белка",
    "description":"Статуя мальчика на бульваре рядом с домом",
    "id":"19",
    "lat":"55.653679",
    "lon":"37.482594",
    "name":"Пр-т Вернадского, д. 127 корп. 3",
    "quest":"Животное на плече мальчика"
  },
  {
    "answer":"5",
    "description":"Памятная стела",
    "id":"22",
    "lat":"55.6765923",
    "lon":"37.4664903",
    "name":"Мичуринский пр-т, Олимпийская деревня, д. 3",
    "quest":"Кол-во букв \"О\" в надписи"
  },
  {
    "answer":"ИК-6АМ",
    "description":"\"Катюша\" перед входом в музей",
    "id":"23",
    "lat":"55.676922",
    "lon":"37.467027",
    "name":"Мичуринский пр-т, Олимпийская деревня, д. 3",
    "quest":"Модель правой передней шины"
  },
  {
    "answer":"верблюд",
    "description":"Огороженная детская площадка во дворе дома",
    "id":"24",
    "lat":"55.670418",
    "lon":"37.472722",
    "name":"Ул. Академика Анохина, д. 4 корп. 2-3",
    "quest":"Животное, в форме которого выполнены качели"
  },
  {
    "answer":"3",
    "description":"Памятник",
    "id":"25",
    "lat":"55.680452",
    "lon":"37.533106",
    "name":"Угол Ленинского пр-та и ул. Крупской",
    "quest":"Общее кол-во букв \"К\" во всех надписях на памятнике и постаменте"
  },
  {
    "answer":"4",
    "description":"Надпись на фасаде на уровне 1-го этажа",
    "id":"26",
    "lat":"55.762035",
    "lon":"37.618433",
    "name":"Ул. Петровка, д. 8",
    "quest":"Кол-во литер \"Т\""
  },
  {
    "answer":"33",
    "description":"Дверь на южной стороне дома",
    "id":"28",
    "lat":"55.7717816",
    "lon":"37.6249337",
    "name":"Трубная ул., д. 27 стр. 1",
    "quest":"Номер квартиры"
  },
  {
    "answer":"10516",
    "description":"Южная сторона строения",
    "id":"29",
    "lat":"55.737454",
    "lon":"37.533609",
    "name":"Кутузовский пр-т, д. 39 стр. 2",
    "quest":"Номер ТП на двери"
  },
  {
    "answer":"подпись",
    "description":"Музей игровых автоматов",
    "id":"30",
    "lat":"55.7359633",
    "lon":"37.625894",
    "name":"Ул. Малая Ордынка, д. 23 стр. 5",
    "quest":"Подпись судьи"
  },
  {
    "answer":"Бородавчатая",
    "description":"Экспозиция стволов деревьев",
    "id":"35",
    "lat":"55.706905",
    "lon":"37.560124",
    "name":"Ул. Косыгина, спуск к Москве-реке между дд. 10 и 18",
    "quest":"Пятое справа бревно, название березы"
  },
  {
    "answer":"11",
    "description":"Фасад дома, выходящий в Безымянный пр.",
    "id":"38",
    "lat":"55.724402",
    "lon":"37.606959",
    "name":"Донская ул., д. 6",
    "quest":"Кол-во полукруглых балконов на фасаде дома"
  },
  {
    "answer":"Изве",
    "description":"Скульптуры вокруг постамента памятника Ленину",
    "id":"39",
    "lat":"55.729427",
    "lon":"37.613221",
    "name":"Калужская пл.",
    "quest":"Видимая часть названия газеты"
  },
  {
    "answer":"подпись",
    "description":"Детская площадка",
    "id":"40",
    "lat":"55.743663",
    "lon":"37.625688",
    "name":"Черниговский пер., д. 9/13",
    "quest":"Подпись судьи"
  },
  {
    "answer":"31 января 1864",
    "description":"Граффити на постройке",
    "id":"43",
    "lat":"55.75626",
    "lon":"37.538088",
    "name":"Шмитовский пр., постройка между д. 28 и д. 30",
    "quest":"Дата на западной стороне"
  },
  {
    "answer":"драпировка",
    "description":"Старая вывеска на восточной стене продуктового магазина",
    "id":"44",
    "lat":"55.761856",
    "lon":"37.537637",
    "name":"Ул. Литвина-Седого, д. 13",
    "quest":"Слово на вывеске"
  },
  {
    "answer":"Гречко",
    "description":"Памятная доска на четной стороне проспекта у пересечения с ул. Барклая",
    "id":"45",
    "lat":"55.736384",
    "lon":"37.515603",
    "name":"Кутузовский пр-т",
    "quest":"Надпись на доске, фамилия полководца, в честь которого назван проспект"
  },
  {
    "answer":"пересменок",
    "description":"Табличка у въезда на АГЗС",
    "id":"46",
    "lat":"55.694985",
    "lon":"37.593233",
    "name":"Ул. Карьер, д. 4",
    "quest":"Что происходит с 7:30 до 8:00?"
  },
  {
    "answer":"7:00-20:00",
    "description":"Табличка на воротах со стороны Ленинского пр-та",
    "id":"47",
    "lat":"55.702973",
    "lon":"37.568001",
    "name":"Ленинский пр-т, д. 42 корп. 2",
    "quest":"Временной интервал, указанный на табличке"
  },
  {
    "answer":"2",
    "description":"Статуи сфинксов перед зданием",
    "id":"48",
    "lat":"55.675996",
    "lon":"37.526565",
    "name":"Ленинский пр-т, д. 88",
    "quest":"Кол-во статуй"
  },
  {
    "answer":"подпись",
    "description":"Площадка во дворе дома.",
    "id":"50",
    "lat":"55.678748",
    "lon":"37.563032",
    "name":"Профсоюзная ул., д. 26/44",
    "quest":"Подпись судьи"
  },
  {
    "answer":"14 га",
    "description":"Информационный стенд напротив",
    "id":"51",
    "lat":"55.709954",
    "lon":"37.518086",
    "name":"Ул. Дружбы, д. 6",
    "quest":"Общая площадь объекта"
  },
  {
    "answer":"4 (и 2 на боковом фасаде)",
    "description":"Атланты на фасаде",
    "id":"53",
    "lat":"55.754914",
    "lon":"37.627383",
    "name":"Ул. Ильинка, д. 8",
    "quest":"Кол-во атлантов"
  },
  {
    "answer":"Руся",
    "description":"Лошадь с чёрной гривой во дворе, правая передняя нога",
    "history":"Шелкоткацкая фабрика \"Красная Роза\", основанная в 1870-х годах, занимала почти целый квартал между улицами Льва Толстого и Тимура Фрунзе. Первоначально фабрика принадлежала промышленникам Жиро, а название \"Красная Роза\" получила в 1924 году в честь Розы Люксембург. Сейчас на месте фабрики, закрытой в 1990-х годах, формируется деловой квартал \"Красная Роза 1875\". Его строительство началось в 2003 году, но еще не завершено. Это один из наиболее масштабных проектов реконструкции фабричной территории, выполняемых на территории Москвы. Новые стоящиеся корпуса делового центра получили именные названия в память наиболее известных промышленников дореволюционной России. Расписанные фигуры лошадей, стоящие перед корпусом \"Морозов\", участники соревнований могли видеть и в прошлом году. Лошади переехали на \"Красную Розу\" с Самокатной улицы вместе с офисом компании \"Яндекс\".",
    "id":"54",
    "lat":"55.733603",
    "lon":"37.587805",
    "name":"Ул. Льва Толстого, д. 16",
    "quest":"Надя и Мария и кто?"
  },
  {
    "answer":"Мировая победа",
    "description":"Торцевая стена дома",
    "id":"57",
    "lat":"55.748542",
    "lon":"37.60581",
    "name":"Малый Знаменский пер., д. 8",
    "quest":"Надпись под крышей"
  },
  {
    "answer":"2",
    "description":"Дом-коммуна",
    "id":"58",
    "lat":"55.757025",
    "lon":"37.58111",
    "name":"Новинский б-р., д. 25 стр. 1",
    "quest":"Кол-во вентиляционных шахт во дворе дома"
  },
  {
    "answer":"подпись",
    "description":"ЦРТДиЮ \"Планета\"",
    "id":"60",
    "lat":"55.704369",
    "lon":"37.578956",
    "name":"Пр-т 60-летия Октября, д. 4",
    "quest":"Подпись судьи"
  },
  {
    "description":"Композиция с человеческими фигурами у пересечения центральной аллеи и аллеи, идущей от д. 28 по Удальцова",
    "id":"61",
    "lat":"55.683264",
    "lon":"37.495751",
    "name":"Парк 50-летия Октября",
    "quest":"Суммарное кол-во пуговиц на рубахах балалаечников"
  },
  {
    "answer":"92",
    "description":"Памятная табличка на здании",
    "id":"62",
    "lat":"55.683273",
    "lon":"37.491796",
    "name":"Ул. Удальцова, д. 40А",
    "quest":"Сумма всех цифр на табличке"
  },
  {
    "answer":"Рисунок",
    "description":"Фонари перед домом",
    "id":"64",
    "lat":"55.694355",
    "lon":"37.486037",
    "name":"Мичуринский пр-т, д. 54 корп. 4",
    "quest":"Зарисовать форму фонарного столба"
  },
  {
    "answer":"12 Вольт",
    "description":"Ржавая табличка на воротах",
    "id":"68",
    "lat":"55.717071",
    "lon":"37.475253",
    "name":"Нежинская ул., д. 3",
    "quest":"Максимальное допустимое напряжение"
  },
  {
    "answer":"432",
    "description":"Дом \"на ножках\"",
    "id":"69",
    "lat":"55.727122",
    "lon":"37.475361",
    "name":"Славянский б-р, д. 1",
    "quest":"Максимальный номер квартиры"
  },
  {
    "answer":"подпись",
    "description":"Музей частных коллекций \"Автовилль\"",
    "id":"70",
    "lat":"55.7310975",
    "lon":"37.5777054",
    "name":"Ул. Усачева, д. 2 стр. 1",
    "quest":"Подпись судьи"
  },
  {
    "answer":"Зорин",
    "description":"Памятная доска на доме",
    "id":"71",
    "lat":"55.731877",
    "lon":"37.47373",
    "name":"Ул. Герасима Курина, д. 14 корп. 3",
    "quest":"Фамилия супрефекта"
  },
  {
    "answer":"107",
    "description":"Старая вывеска книжного магазина",
    "id":"74",
    "lat":"55.751314",
    "lon":"37.500776",
    "name":"Новозаводская ул., д. 25 корп. 6",
    "quest":"Номер магазина на вывеске"
  },
  {
    "answer":"14",
    "description":"Стенды для игры в крестики-нолики во дворе",
    "id":"76",
    "lat":"55.748047",
    "lon":"37.514437",
    "name":"Новозаводская ул., д. 2",
    "quest":"Суммарное кол-во кубиков с нарисованными крестиком и ноликом на противоположных сторонах"
  },
  {
    "answer":"RATP",
    "description":"Памятная табличка в переходе у выхода, оформленного в духе парижской подземки",
    "id":"77",
    "lat":"55.744078",
    "lon":"37.567156",
    "name":"Ст. м. \"Киевская\"",
    "quest":"Аббревиатура латиницей"
  },
  {
    "answer":"24",
    "description":"Мост через искусственный водоем в районе д. 6",
    "id":"79",
    "lat":"55.747747",
    "lon":"37.56581",
    "name":"Украинский б-р",
    "quest":"Общее кол-во ступеней с обеих сторон моста"
  },
  {
    "answer":"подпись",
    "description":"Двор рядом с домом",
    "id":"80",
    "lat":"55.7321667",
    "lon":"37.5379872",
    "name":"Ул. Пудовкина, д. 6 корп. 2",
    "quest":"Подпись судьи"
  },
  {
    "answer":"12",
    "description":"Мемориальная табличка народной артистки",
    "id":"81",
    "lat":"55.75136",
    "lon":"37.565381",
    "name":"Кутузовский пр-т, д. 2/1",
    "quest":"Кол-во отверстий перфорации на изображении киноплёнки"
  },
  {
    "answer":"МПП",
    "description":"Кирпичные ворота во дворе дома",
    "history":"Бадаевский пивоваренный завод основан в 1875 году купцом Г. С. Морозовым и первоначально назывался Трёхгорным по \"Трём горам\" - местности на противоположном левом берегу реки Москвы. Это один из старейших действовавших до последнего времени пивзаводов столицы. В 1890-х годах по проекту Р. И. Клейна были выстроены производственные корпуса, существующие до настоящего времени. В 1930-е годы завод получил имя Бадаева. В наши дни начат вывод завода с лакомых площадей в центре города, напротив \"Сити\". На его месте планируется постройка жилого комплекса, в составе которого должна быть сохранена только небольшая часть старых зданий.",
    "id":"82",
    "lat":"55.749856",
    "lon":"37.560429",
    "name":"Кутузовский пр-т, д. 8",
    "quest":"Аббревиатура из трёх букв на воротах"
  },
  {
    "answer":"8",
    "description":"Усадебный дом в парке через дорогу",
    "id":"87",
    "lat":"55.735636",
    "lon":"37.448076",
    "name":"Большая Филевская ул., д. 65",
    "quest":"Кол-во окон в световом фонаре на крыше усадебного дома"
  },
  {
    "answer":"8",
    "description":"Рисунок на фасаде",
    "id":"89",
    "lat":"55.758593",
    "lon":"37.560329",
    "name":"Ул. Трёхгорный Вал, д. 6",
    "quest":"Кол-во видимых зубцов стены"
  },
  {
    "answer":"подпись",
    "description":"Биологический музей им. К. А. Тимирязева",
    "id":"90",
    "lat":"55.7640985",
    "lon":"37.571708",
    "name":"Малая Грузинская ул., д. 15",
    "quest":"Подпись судьи"
  },
  {
    "answer":"контора",
    "description":"Фасад дома напротив",
    "history":"Территория, в наши дни занятая бизнес-центром \"Луч\", была застроена в конце XIX века. В 1899 году по проекту архитектора Александра Ивановича Роопа здесь был сооружен казенный винный склад. Его краснокирпичные корпуса сохранились в составе бизнес-центра до сих пор. В конце 1920-х годов корпуса винных складов были реконструированы и заняты заводом \"Электросвет\". Заводская продукция использовалась при оборудовании московского метрополитена, устройстве освещения помещений Кремля и подсветки звезд на кремлевских башнях. В 2000-х годах завод был выведен из Москвы в город Гагарин Смоленской области, а заводские корпуса реконструированы под бизнес-центр.",
    "id":"93",
    "lat":"55.728954",
    "lon":"37.568856",
    "name":"Малая Пироговская ул., д. 17",
    "quest":"Слово на фасаде"
  },
  {
    "answer":"знак",
    "description":"Лестница между домом и строительной площадкой",
    "id":"96",
    "lat":"55.7434316",
    "lon":"37.6456726",
    "name":"Котельническая наб., д. 25",
    "quest":"Знак у вершины лестницы"
  },
  {
    "answer":"5",
    "description":"Закладной камень в сквере",
    "id":"97",
    "lat":"55.7478098",
    "lon":"37.6469278",
    "name":"Сквер на углу Николоямской ул. и Яузской ул.",
    "quest":"Кол-во твердых знаков"
  },
  {
    "answer":"14",
    "description":"См. картинку. Площадь к северу от объекта, отмеченного крестиком.",
    "id":"102",
    "image":"http://img.runcity.org/img/routes/msk2010-cp102-med.jpg",
    "longanswer":"На прилагающейся к загадке картинке квадратами были обозначены станции метро, а стрелки вправо-влево указывали стороны, в которую на соответствующей станции выполняется выход из вагона поезда. Изображен участок Арбатско-Покровской линии метрополитена от \"Киевской\" до \"Митино\", наиболее изобилующий станциями, выход из вагона на которых осуществляется в \"неправильную\" сторону - направо по ходу движения поезда. Обозначенная крестиком станция - \"Крылатское\", рядом с которой на площади Защитников Неба и следовало пересчитать буквы \"Д\" на памятнике. Ответ: 14",
    "name":"Загадка",
    "quest":"Кол-во литер \"Д\" в надписях на памятнике"
  },
  {
    "answer":"4",
    "description":"Самую заметную из московских построек этого инженера и памятник ему разделяют четыре перегона метро.",
    "id":"103",
    "longanswer":"В загадке были загаданы \"Шуховская\" башня на Шаболоке и памятник инженеру Шухову, не так давно открытый на Тургеневской площади. От станции \"Шаболовская\" до станции \"Тургеневская\" - четыре перегона по Калужско-Рижской линии метрополитена. Ответ: 4",
    "name":"Загадка",
    "quest":"Скульптурные композиции у памятника. Кол-во шестеренок."
  },
  {
    "answer":"6",
    "description":"Материал, из которого выполнен второй этаж дома 5 в этом переулке, противоречит названию переулка.",
    "id":"104",
    "longanswer":"В Погорельском переулке Замоскворечья, среди множества каменных зданий, имеется дом с деревянным вторым этажом - дом 5, на нём и помещена соответствующая доска. Ответ: 6",
    "name":"Загадка",
    "quest":"Табличка слева от двери, выходящей в переулок. Кол-во букв \"О\" в верхней строке таблички."
  },
  {
    "answer":"2",
    "description":"Название этого переулка напоминает о московской боярской семье, достигшей наибольших высот. Найдите в нём дом, увешанный наибольшим количеством мемориальных досок.",
    "id":"105",
    "longanswer":"Был загадан Романов переулок, названный по боярской семье Романовых, в начале XVII века достигшей наибольших высот - ставшей царской. Дом 3 в Романовом переулке в 1920-30-х именовался \"5-м домом Советов\" - в нём проживало огромное количество представителей высших слоёв советской номенклатуры, в память о чём весь дом обвешан мемориальными досками. Одна из них посвящена авиаконструктору Мясищеву. Ответ: 2",
    "name":"Загадка",
    "quest":"Мемориальная доска с изображением самолёта. Кол-во букв \"Ц\""
  },
  {
    "answer":"1964",
    "description":"Изображение города с рекой на боку синегривой лошади во дворе дома на улице Льва Толстого.",
    "id":"106",
    "longanswer":"Во дворе дома 16 по улице Льва Толстого, у офиса компании \"Яндекс\" стоят две лошади. Участники соревнований могли видеть их на БГМ-2009 у старого офиса \"Яндекса\" на Самокатной улице. Картина на боку синегривой лошади изображала вид на Кремль из Замоскворечья. В месте, откуда можно было написать подобный пейзаж, есть единственная памятная доска, которая и была загадана. Ответ: 1964",
    "name":"Загадка",
    "quest":"Представьте, что вы пишете такой же пейзаж. Развернитесь, и на памятной плите найдите первый упоминаемый там год"
  },
  {
    "answer":"1",
    "description":"См. аэрофотоснимок. У места, где находился торец взлетно-посадочной полосы, выйдите на берег.",
    "id":"107",
    "image":"http://img.runcity.org/img/routes/msk2010-cp107-med.jpg",
    "longanswer":"На аэрофотоснимке изображена взлетно-посадочная полоса завода № 22 в Филях - ныне КБ им. Хруничева. Сейчас завод занимается выпуском космической техники, а примерно на месте полосы проходит Филевский бульвар. От его восточного края хорошо видна причальная стенка на противоположном берегу реки Москвы с кранами и граффити в виде одного огромного цветка. Ответ: 1",
    "name":"Загадка",
    "quest":"Кол-во цветков, нарисованных на причальной стенке с кранами на противоположном берегу."
  },
  {
    "answer":"20",
    "description":"Найдите мемориальную доску необычной формы на доме пр. Вернадского, д.125. На самом деле, герой этой мемориальной доски жил совсем в другом месте.",
    "id":"108",
    "longanswer":"Доска на доме по улице Вернадского посвящена героям популярного в прошлом кинофильма \"Ирония судьбы\". В соответствии со сценарием фильма герой - Евгений Лукашин, обитал в доме 25 на 3-й улице Строителей. Сейчас такой улицы в Москве нет, но до 1963 года так называлась улица Марии Ульяновой. В первом подъезде дома 25 по Марии Ульяновой - 20 квартир. Ответ: 20",
    "name":"Загадка",
    "quest":"Номер последней квартиры в подъезде, где жил герой мемориальной доски."
  },
  {
    "answer":"Брежнев",
    "description":"См. картинку. Правобережная опора, на которую в наши дни опирается арка моста, показанного на картинке. Мемориальная доска на опоре.",
    "id":"109",
    "image":"http://img.runcity.org/img/routes/msk2010-cp109-med.jpg",
    "longanswer":"На картинке изображен железнодорожный Андреевский мост через Москву-реку. В 1990-х годах при реконструкции моста его старая арочная часть была перевезена ниже по течению реки и поставлена в качестве пешеходного моста между Фрунзенской и Пушкинской набережными. Сейчас перевезенная арка старого моста опирается со стороны правого берега на новую опору, украшенную большой круглой памятной доской, рассказывающей об истории моста. Последняя фамилия на доске - Брежнев. Ответ: Брежнев",
    "name":"Загадка",
    "quest":"Надпись на доске, последняя из фамилий"
  },
  {
    "answer":"Подпись",
    "description":"Космонавт - революционер - президент - генеральный секретарь - академик - проповедник.",
    "id":"110",
    "longanswer":"Была загадана последовательность видных деятелей второй половины ХХ века, в честь которых названы площади у станций метро Калужско-Рижской линии. У станции \"Ленинский Проспект\" - площадь Гагарина; у станции \"Академическая\" - площадь Хо Ши Мина; у станции \"Профсоюзная\" - площадь Иосипа Броз Тито; у станции \"Новые Черемушки\" до начала 1990-х существовала площадь Брежнева, после краха СССР лишенная названия и ныне безымянная; у станции \"Калужская\" - площадь Академика Келдыша; наконец, у станции \"Беляево\" - площадь Мартина Лютера Кинга. На площади Иосипа Броз Тито, во дворе дома с памятной доской в честь Тито, и располагался живой КП. Ответ: Подпись",
    "name":"Загадка",
    "quest":"Зайдите во двор дома, на котором висит мемориальная табличка, объясняющая, причем тут президент. Подпись"
  },
  {
    "answer":"знак",
    "description":"См. фото. Место, с которого выполнен снимок.",
    "id":"112",
    "image":"http://img.runcity.org/img/routes/msk2010-cp112-med.jpg",
    "longanswer":"На этом несложном фото-КП показан вид на Высокопетровский монастырь из Печатникова переулка. Знак в арке дома 5, от которого сделан снимок, в виде стилизованного ситечка напоминал о том, что именно тут для кинофильма \"Двенадцать стульев\" снимался дом Эллочки Людоедки. Ответ: знак",
    "name":"Загадка",
    "quest":"Знак в арке"
  },
  {
    "answer":"Камчатка",
    "description":"См. фото. Дом напротив.",
    "id":"114",
    "image":"http://img.runcity.org/img/routes/msk2010-cp114-med.jpg",
    "longanswer":"Это еще одно несложное фото-КП с видом фрагмента костела Непорочного Зачатия на Большой Грузинской. На доме напротив, в котором жил Владимир Высоцкий, помимо официальной памятной доски есть и неофициальная, установленная в память поэта жителями Камчатки Ответ: Камчатка",
    "name":"Загадка",
    "quest":"Название полуострова на памятной доске"
  },
  {
    "answer":"2",
    "description":"Когда-то здесь перерезали горло Михаилу Александровичу, разбив бутылку. Но не розочкой, а более сложным путём. В наши дни жители этих мест выступили против установки памятника кухонной утвари.",
    "id":"115",
    "longanswer":"В загадке упоминались события романа \"Мастер и Маргарита\" - на масле из разбитой бутылки поскользнулся М. А. Берлиоз, упавший под колеса трамвая, отрезавшего ему голову (и попутно перерезавший горло). Не так давно в сквере на Патриарших хотели поставить грандиозный памятник литературным героям романа, с огромным примусом, но против выступили жители окрестных домов, и затею с памятником отложили. На углу сквера со времен, когда мимо Патриарших ходил трамвай, остался павильон с надписью МОГЭС и двумя оконцами. Ответ: 2",
    "name":"Загадка",
    "quest":"В загаданном сквере найдите постройку с буквами МОГЭС. Кол-во оконных проемов"
  },
  {
    "answer":"Унiверсит",
    "description":"См. картинку. Картина в месте, отмеченном стрелкой",
    "id":"116",
    "image":"http://img.runcity.org/img/routes/msk2010-cp116-med.jpg",
    "longanswer":"На картинке показана схема пересадочного узла станции \"Киевская\". Стрелка указывает на один из пилонов станции \"Киевская-кольцевая\". Из-за ошибки автора картинки, стрелка указывала не на нужный пилон с изображением киевского университета с надписью на фасаде, а на пилон, ему противоположный. Это, однако, не помешало участникам разгадать задание - иных зданий с надписями на мозаиках станции нет. Ответ: Унiверсит",
    "name":"Загадка",
    "quest":"Надпись на здании, изображенном на картине"
  },
  {
    "answer":"Жить стало веселей",
    "description":"Единственный в Москве памятник, изображающий уголовника и рецидивиста, находится далеко от мест, где пребывают настоящие правонарушители. В то же время, он стоит рядом с воротами заведения, из которого \"вышел\" этот уголовник, на улице, своим названием напоминающей об этом заведении.",
    "id":"118",
    "longanswer":"Был загадан памятник киноактеру Евгению Леонову в образе вора-рецидивиста \"Доцента\" - героя популярного кинофильма \"Джентльмены удачи\", поставленный у здания киностудии \"Мосфильм\", на которой и снят этот фильм, на Мосфильмовской улице. На руке скульптуры выгравирована надпись \"Жить стало веселее\". Ответ: Жить стало веселей",
    "name":"Загадка",
    "quest":"Надпись на правой руке скульптуры"
  },
  {
    "answer":"советского",
    "description":"Вначале проспект был отдан маршалу. Затем маршал оказался в опале, а его проспект присоединили к владению генерал-фельдмаршала. Как напоминание о прежнем владельце осталась только небольшая стела, стоящая у места, где встречаются два генерал-фельдмаршала.",
    "id":"119",
    "longanswer":"Загадка напоминала об еще одном топониме, появившемся в последние десятилетия советской власти и убранном с карты сразу после краха СССР. В 1980-х участок Можайского шоссе был назван проспектом Маршала Гречко. После краха СССР проспект Гречко присоединили к Кутузовскому проспекту. Как напоминание о существовании проспекта Гречко остался мемориальный знак в виде доски у соединения Кутузовского проспекта и улицы Барклая-де-Толли. И Кутузов, и Барклай имели высший армейскмй чин в императорской армии - оба были генерал-фельдмаршалами. Ответ: советского",
    "name":"Загадка",
    "quest":"Прилагательное перед словом \"государства\" в надписи на стеле"
  },
  {
    "description":"См. картинку. Место на берегу реки в направлении, указанном стрелкой.",
    "id":"120",
    "image":"http://img.runcity.org/img/routes/msk2010-cp120-med.jpg",
    "longanswer":"Баяны на картинке соответствуют группам 5- и 9-этажных домов в районе Матвеевское. Стрелка указывала место в долине Сетуни, где в этот раз располагалось живое КП \"Татары\".",
    "name":"Загадка",
    "quest":"Отметка судьи"
  },
  {
    "answer":"23216",
    "description":"Бибигон и Незнайка бежали по Москве, переговариваясь по рации. Произошёл такой диалог: Б: Если мы так и будем бежать по этим улицам, то никогда не встретимся. Ведь они параллельны! Н: Ещё как встретимся! Это доказал тот, по чьей улице я сейчас бегу. Б: Незнайка, ты опять всё перепутал! Ничего такого он не доказывал! Тем не менее, через некоторое время улицы, по которым бежали наши герои, сменили свои названия, а ещё позже они встретились на перекрёстке, хотя никто из них никуда не сворачивал.",
    "id":"121",
    "longanswer":"Незнайка напоминал Бибигону популярное заблуждение - \"в геометрии Лобачевского параллельные прямые пересекаются\". На самом деле теория Лобачевского сложнее. Московские улица Лобачевского и параллельная ей улица Удальцова продолжаются улицами Обручева и Новаторов соответственно. У пересечения последних и расположена требуемая ТП. Ответ: 23216",
    "name":"Загадка",
    "quest":"Во дворе к северо-западу от места встречи найдите трансформаторную подстанцию, украшенную разноцветными буквами. Номер ТП (пять цифр)."
  },
  {
    "answer":"26",
    "description":"В Москве есть несколько проспектов, на которых можно увидеть все виды наземного общественного транспорта. Выберите среди них проспект с самым длинным названием.",
    "id":"122",
    "longanswer":"Среди проспектов Москвы, на которых можно встретить станции метро, трамваи, троллейбусы, автобусы и всевездесущие маршрутные такси - Буденного, Зеленого, Мира, Ломоносовского, Нахимовского - самое длинное название у Ломоносовского. На нём во дворе дома 29 и есть искомая ТП с грибами. Ответ: 26",
    "name":"Загадка",
    "quest":"Во дворе дома 29 по проспекту найдите ТП с грибами. Кол-во шляпок грибов."
  },
  {
    "description":"Этой особенностью обладает множество московских переулков и улиц. Однако упоминания о ней есть только в названиях трёх переулков. У начала самого западного из этих переулков найдите карту с изображениями домов.",
    "id":"123",
    "longanswer":"Эту Загадку с подвохом пришлось снять из-за ошибки в формулировке. Вместо текста \"в правом нижнем углу карты\" в ней должен был быть текст \"в правом нижнем углу плаката\". Участники достаточно быстро догадывались, что особенность переулков - их кривизна, и находили плакат с картой на торце дома в Кривоарбатском. Однако сумма цифр в адресе дома в \"правом нижнем углу карты\" - дома 17 - давала 8, а дом 8 по Плотникову переулку нежилой. подъезде дома 2 по Плотникову. Те же, кто пошёл бы проверять реальный текст на адресной табличке музея Скрябина, узнали что на ней написано \"дом 1 стр. 1-3\", а, значит, считать квартиры наддо в первом подъезде дома 6 по Плотникову.",
    "name":"Загадка",
    "quest":"Сумма цифр на адресной табличке дома, изображение которого помещено в правом нижнем углу карты, даст номер дома в переулке, в который загаданный переулок упирается своим дальним концом. Сколько квартир в первом подъезде этого дома?"
  },
  {
    "answer":"1829",
    "description":"И перед Спасскими, и перед Варварскими можно увидеть постройки с девиантным поведением. Между этих двух найдите третью, с такой же особенностью.",
    "id":"124",
    "longanswer":"Девиация - в переводе на русский - отклонение. И перед Спасскими, и перед Варварскими воротами стоят церкви с отлонившимися от вертикальной оси колокольнями - храм Покрова на Рву (собор Василия Блаженного) - и церковь Всех Святых на Кулишках. Этот наклон заметен визуально. На соединяющей ворота улице Варварка стоит ещё одна церковь с визуально заметным наклонном колокольни - церковь святого Максима. На ней и следовало искать памятную доску с датой. Ответ: 1829",
    "name":"Загадка",
    "quest":"Памятная доска на стене третьей постройки. Самая поздняя из дат"
  },
  {
    "answer":"12",
    "description":"Отцу в нашем городе три улицы дали, ещё одна сыну его досталась. На средней из отцовских улиц на нечётной стороне девятый дом найди. Во дворе дома того за забором два домика малых стоят. Оба домика - без одной стены, да окна в них есть.",
    "id":"125",
    "longanswer":"В загадке обыгрывался факт наличия в Москве трёх улиц, названных в честь Михаила Фрунзе - 1-й, 2-й и 3-й Фрунзенской, и единственной улицы, названной в честь его сына - Тимура Фрунзе. Во дворе дома 9 по 2-й Фрунзенской - средней из трёх - на детской площадке и стоят загаданные домики. Ответ: 12",
    "name":"Андрейко, сын Бутовский, и Бибигонище Поганое. Бэгэйская сказка. Первый совет Бабы-Яги",
    "quest":"Коли хочешь Бибигонище одолеть - окна те пересчитай, да в бумагу подорожную запиши."
  },
  {
    "answer":"2",
    "description":"Среди всех улиц этого не существующего города, лишь одну можно найти с двух сторон от бывшей центральной улицы города. Напротив дома 8 по этой улице найдите памятник.",
    "id":"126",
    "longanswer":"Несуществующий город - город Кунцево, в 1960-х поглощенный Москвой. Его главная улица - Можайское шоссе. Из всех улиц старого Кунцева Можайское шоссе пересекает только улица Багрицкого. Рядом с домом 8 по улице Багрицкого стоит памятник этому поэту. Ответ: 2",
    "name":"Загадка",
    "quest":"Кол-во штыков"
  },
  {
    "description":"См. картинку. Построив прямую линию, соединявшую обе часовые башенки, найдите на ней солнечные часы.",
    "id":"127",
    "image":"http://img.runcity.org/img/routes/msk2010-cp127-med.jpg",
    "name":"Загадка",
    "quest":"Какие римские цифры, соответствующие часам суток, отсутствуют на циферблате?"
  },
  {
    "answer":"VII, VIII",
    "description":"См. картинку. Построив прямую линию, соединявшую обе часовые башенки, найдите на ней солнечные часы.",
    "id":"127",
    "image":"http://img.runcity.org/img/routes/msk2010-cp127-med.jpg",
    "longanswer":"На фотографиях показаны часовые башенки на доходных домах страхового общества \"Россия\", построенных незадолго до революции. Один из домов сохранился до наших дней в первозданном виде - он стоит на Сретенском бульваре. Второй - на Лубянской площади - в середине ХХ века был перестроен и всем известен как здание КГБ. Однако сами часы на его фасаде уцелели. На прямой, соединяющей обе башенки, находится флигель костела святого Людовика (Малая Лубянка, 12) с солнечными часами на стене. На часах нет обозначений часов VII и VIII. Ответ: VII, VIII",
    "name":"Загадка",
    "quest":"Какие римские цифры, соответствующие часам суток, отсутствуют на циферблате ?"
  },
  {
    "answer":"К",
    "description":"\"Дешевый хлеб в шаговой доступности от любого дома!\", \"Африканское животное выпекается на нашей фабрике!\", \"Постой, автомобилист и пешеход! У нас самое вкусное печение!\". Слегка измененные эти и другие слоганы венчал один главный и наиболее известный. До определенного момента его можно было встретить на доме в центре Москвы. Затем он исчез, но в 1997 году его вернули на место.",
    "id":"128",
    "longanswer":"Были перефразированы лозунги из рекламы \"Моссельпрома\", украшавшие дом Моссельпрома у Арбатских ворот. Огромная настенная реклама 1920-х позже была утрачена, и восстановлена в 1997 году. Ответ: К",
    "name":"Загадка",
    "quest":"Стена здания. Лишняя в современной орфографии буква."
  },
  {
    "answer":"2-м и 3-м",
    "description":"Найдите в Москве квартал, ограниченный четырьмя именованными дорогами, такими что: все, кроме первой, содержат букву \"Л\" в названии; на всех, кроме второй, есть дом 70; все, кроме третьей, названы в честь учёных; на всех, кроме четвёртой, есть хотя бы одна станция метро",
    "id":"129",
    "longanswer":"Был загадан квартал, ограниченный между проспектами Вернадского, Ленинским и улицами Лобачевского и Удальцова, обнаруживаемый анализом карты города. Дворик у стены дома 81 по Вернадского украшен, помимо прочего, садовым пугалом. Ответ: 2-м и 3-м",
    "name":"Загадка",
    "quest":"Два из этих названий содержат одинаковое количество букв. Возведя его в квадрат, получите номер дома. Найдите внутри квартала этот дом. Между каким подъездами поставлено пугало?"
  },
  {
    "answer":"Печать",
    "description":"И последнее что скажу тебе. Как на площадь, в честь хорвата названную, прийдешь - обернись, да оглянись. На доме угловом доска повешена, на доске всё про того хорвата буквами прописано. Смело во двор дома этого заходи. Как во двор войдёшь, да судей увидишь - трижды посолонь обернись, дважды в ладони хлопни, подпрыгни, да скажи - \"Сгинь зараза\". Тут Бибигонищу карачун настанет.",
    "id":"130",
    "longanswer":"В загадке обыгрывается площадь Иосипа Броз Тито - лидер социалистической Югославии был хорватом по национальности. На ней во дворе дома с памятной доской в честь Тито и сидели судьи. Ответ: Печать",
    "name":"Последний совет Бабы-Яги",
    "quest":"О том и судьи тебе в книге подорожной печать поставят."
  },
  {
    "answer":"16",
    "description":"Единственная в Москве улица-набережная. Мемориальная доска на доме.",
    "id":"131",
    "longanswer":"Болотная улица, переходящая в Болотную набережную - единственная в городе. На стене одного из домов по Болотной помещена памятная доска Татьяне Макаровой. Ответ: 16",
    "name":"Загадка",
    "quest":"Номер дома, в котором жила однофамилица народной артистки с КП81 и полная тёзка члена оргкомитета."
  },
  {
    "description":"Большинство улиц и переулков в этой части Москвы получило названия по ремеслу их жителей. Среди всех названий выберите наиболее тряпичное.",
    "id":"132",
    "longanswer":"Вторая снятая загадка - в этот раз из-за невнимательности при постановке, лишающей участников возможности дать единственно верный ответ. Участники достаточно быстро разгадывали, что задуман Скатерный переулок. Но во дворе дома 11 по переулку, на стенах стадиона, помимо изображения церкви Симеона Столпника на Поварской, участники смогли найти достоверные изображения церквей Большого Вознесения и Борисоглебской часовни на Арбатской площади. Интриги придало и то, что загаданная стена у церкви святого Симеона в день соревнований была перезакрашена граффитчиками, так что ожидавшееся имя MASHA было утрачено.",
    "name":"Загадка",
    "quest":"Во дворе дома 11 на стене стадиона найдите изображение церкви. Отправляйтесь к прототипу изображенного здания. Граффити на противоположной церкви стороне улицы. Женское имя на заборе, справа от огромного человеческого лица."
  },
  {
    "answer":"1",
    "description":"Надо тебе, Андрейко, из городу прочь идти. Как из под земли вылезешь, да на холм выберешься - стань к Москве задом, к Замкадью передом, да вокруг посмотри. Направо - три креста стоят. Налево - ещё три. Чуть вперёд пройдешь - седьмой крест покажется. От седьмого креста направо три кольца завиднеются. Посреди среднего кольца - домик белый, на стене домика белого - Царевна-Лебедь красками изображена.",
    "id":"133",
    "longanswer":"Рядом с конечной станцией метро \"Юго-Западная\" стоят две группы, каждая - из трех крестообразных в плане домов. Чуть дальше в сторону области находится седьмой крестообразный дом, от которого видны построенные в виде колец корпуса домов 26, 30 и 38 по Анохина. В дворе среднего из \"колец\" - дома 30 - и находилась заданная ТП Ответ: 1",
    "name":"Второй совет Бабы-Яги",
    "quest":"Коли хочешь Бибигонище одолеть - все корабли, на море рядом с Царевной-Лебедью нарисованные, пересчитай, да в бумагу подорожную запиши."
  },
  {
    "answer":"2",
    "description":"Найдите в Москве квартал, ограниченный четырьмя именованными дорогами, такими что: все, кроме первой, содержат букву \"Л\" в названии; на всех, кроме второй, есть дом 70; все, кроме третьей, названы в честь учёных; на всех, кроме четвёртой, есть хотя бы одна станция метро.",
    "id":"134",
    "longanswer":"Был загадан квартал, ограниченный между проспектами Вернадского, Ленинским и улицами Лобачевского и Удальцова, обнаруживаемый анализом карты города. ТП по адресу Удальцова, д. 3 корп. 1 стр. 2 укращена, помимо прочего, мыльными пузырями, а сумма цифр даёт адрес Лобачевского, 16, интересный нестандартным оформлением газона перед подъездом. Ответ: 2",
    "name":"Загадка",
    "quest":"В начале последней по алфавиту улицы, ограничивающей квартал, найдите ТП с мыльными пузырями. К сумме цифр на адресной табличке, помещенной на ТП, прибавьте 10. Дом, находящийся в квартале, с номером, равным полученному числу. Газон с шарами у подъезда. К"
  },
  {
    "answer":"5, 6",
    "description":"Вспомнив название церкви, стоящей напротив восточного конца этого переулка, можно подумать, что он получил своё название по этой постройке. Однако на самом деле переулок получил название по другой церкви другой конфессии, находившейся на повороте переулка и сломанной задолго до постройки ныне существующего церковного здания.",
    "id":"135",
    "longanswer":"Был загадан Петроверигский переулок, названный по православной Петроверигской церкви, стоявшей у изгиба переулка и сломанной в середине XIX века. Сейчас напротив восточного конца переулка стоит лютеранская Петропавловская церковь, современное здание которой построено в начале ХХ века. Ответ: 5, 6",
    "name":"Загадка",
    "quest":"Во дворе дома 10 по этому переулку найдите балкон без дна. Цифры на дверях подъездов под балконом"
  },
  {
    "answer":"7",
    "description":"Мисс. Mallard, а с ней Jack, Kack, Lack, Mack, Nack, Ouack, Pack, и Quack живут в парках Москвы и Бостона. Но в Москве им не придется переходить дорогу что бы искупаться.",
    "id":"136",
    "longanswer":"Были загаданы имена мамы-утки и её детей из американской сказки. Памятник утятам был поставлен в Бостоне, в США, а его копию в 1990-х подарила Москве Барбара Буш. Подаренные утята поставлены на берегу Новодевичьего пруда. Ответ: 7",
    "name":"Загадка",
    "quest":"Встаньте рядом с Packом и посмотрите на другой берег. Кол-во видимых башен на стене"
  },
  {
    "answer":"533",
    "description":"См. картинку. С перекрестка, ближайшего к зданию, с которого сделан кадр, идите в переулок. На первой развилке сверните направо, на второй - налево, на третьей направо, на четвертой - снова направо. По правой стороне переулка, в который вы попадёте, на стене здания найдите найдите треугольный нивелирный знак.",
    "id":"137",
    "image":"http://img.runcity.org/img/routes/msk2010-cp137-med.jpg",
    "longanswer":"На снимке дан вид с дома 11 по Покровскому бульвару. Сам дом определяется триангуляцией, после чего двигаясь по заданному алгоритму - Подколокольный - Хитровский - Малый Трехсвятительский - Подкопаевский - участинки попадали в Большой Трехсвятительский и находили нужный нивелирный знак. Ответ: 533",
    "name":"Загадка",
    "quest":"Число в средней строке"
  },
  {
    "answer":"знак",
    "description":"См. картинку. Старая московская площадь, ближайшая к месту съемки. Основание столба у забора строительной площадки.",
    "id":"138",
    "image":"http://img.runcity.org/img/routes/msk2010-cp138-med.jpg",
    "longanswer":"На снимке дан в виде силуэта вид на центр города с восточного края Ивановской горки. Требуемый знак был помещен на заборе вокруг стройки на Хитровской площади. Ответ: знак",
    "name":"Загадка",
    "quest":"Знак"
  },
  {
    "answer":"11",
    "description":"Переулок, название которого созвучно со вторым цветом радуги",
    "id":"139",
    "longanswer":"Второй цвет радуги - оранжевый, по-украински - помаранчевый. Это прилагательное слово за последние годы не раз звучало в СМИ. В Померанцевом переулке Москвы и сделовало считать трубы на доме 7. Ответ: 11",
    "name":"Загадка",
    "quest":"Кол-во водосточных труб на доме 7 в переулке"
  },
  {
    "answer":"подпись",
    "description":"В нашем царстве, в российском государстве, в стольном городе Москве завелось Бибигонище Поганое. Как увидит какого бэгэйца - так схватит и все мозги ему наизнанку вывернет. Узнал о том Андрейко, сын Бутовский, осерчал. \"Ух, доберусь я до тебя\", - думает. \"Недолго тебе, Бибигонище, лютовать осталось\". Взял семок, надел кепку и поехал в центр - надо совета у Бабы Яги спросить. Бабку найти несложно - пацаны на районе подсказали, приметы дали верные. Есть в Москве переулок. Хоть и короток переулок, но с двумя коленцами, да двумя церквами.",
    "id":"140",
    "longanswer":"В разгонном задании был зашифрован Черниговский переулок Москвы - с двумя церквами и двумя изгибами, где участников и встречала, помимо прочего, добрая Баба Яга. Задание, как и задания последующего этапа, были введены в соответствии с большой популярностью у участников термина \"Бибигон\", выявленной в ходе обсуждения перед соревнованиями. Ответ: подпись",
    "name":"Андрейко, сын Бутовский, и Бибигонище-Поганое. Бэгэйская сказка. Зачин.",
    "quest":"Как до конца переулка дойдешь - налево во двор сверни. Там Яга и сидит, как дальше быть - расскажет."
  },
  {
    "answer":"3",
    "description":"В Москве остались три улицы, напоминающие об этой известной боярской фамилии. Одна из них заканчивается на краю Земляного города, вторая - на краю Земляного города начинается. 350 метров к северо-востоку от начала третьей из улиц.",
    "id":"141",
    "longanswer":"Загаданная семья - Воронцовы. Об них напоминают две улицы у Садового кольца - Воронцово Поле и Воронцовская, и одна - в новостройках - Воронцовские Пруды. Отмеченная знаком ТП с картинами, слегка напоминающими работы импрессионистов - у дома 1 по улице Наметкина. Ответ: 3",
    "name":"Загадка",
    "quest":"Стена ТП, отмеченная знаком. Кол-во лодок на море рядом с пароходом с бело-красно-белой трубой."
  },
  {
    "answer":"добро",
    "description":"Название этого города произошло не то от каменистого речного русла, не то от татарской крепости. На улице, названной в честь этого города, у дома, с номером, на 2 меньше максимального по улице, найдите фрегат.",
    "id":"142",
    "longanswer":"В загадке задуман город Кременчуг. В подвале дома 44 по Кременчугской помещена студия \"Фрегат\", среди украшающих её стены картин запись \"3+2\", дающая число 5, а во дворе дома 5 по Кременчугской - ТП с надписями, пропогандирующими \"Добро\". Ответ: добро",
    "name":"Загадка",
    "quest":"Во дворе дома на этой же улице, с номером, равным математическому выражению на стене фрегата, найдите ТП. Самое часто встречающееся слово из пяти букв на стенах ТП."
  },
  {
    "answer":"17:30",
    "description":"См. картинку. В месте, отмеченном крестиком, найдите ТП с изображением высотного дома. Отправляйтесь к зданию, изображение которого помещено под словом \"Газета\".",
    "id":"143",
    "image":"http://img.runcity.org/img/routes/msk2010-cp143-med.jpg",
    "longanswer":"На слепой карте, сделанной из карты 1900-х, изображен современный Шмитовский проезд. Между домами 28 и 30 по проезду - ТП с граффити, в числе которых - изображения дома-музея Горького на Малой Никитской, на котором и следовало искать требуемое объявление. Ответ: 17:30",
    "name":"Загадка",
    "quest":"Надпись на бумаге под стеклом слева от бокового входа. Время."
  },
  {
    "answer":"XVI",
    "description":"Фамилии всем известного революционера-военного и мало известного революционера-фабриканта отличаются лишь одной буквой. В проезде, названном в память фабриканта, между домами 28 и 30 стоит ТП с граффити. На стене ТП найдите карту города.",
    "id":"144",
    "longanswer":"Загаданы фамилии Шмидт - лейтенант, активный участник революции 1905, и Шмит - фабрикант, спонсировавший революционное движение в Москве. Карта помещена на ТП между домами 28 и 30 по Шмитовскому, в её правом нижнем углу - мыс между Москвой-рекой и Водоотводным каналом. На мыс ведет Патриарший мост, между мостом и церковью Николы на Берсеневке - недавно отреставрированное здание. XVI век на памятной доске крайне сомнителен, чем она и забавна. Ответ: XVI",
    "name":"Загадка",
    "quest":"На мыс, изображенный в правом нижнем углу карты, ведет пешеходный мост. Охранная доска на жёлтом здании между мостом и церковью. Самый ранний век, упомянутый на доске."
  },
  {
    "answer":"5",
    "description":"Есть в Москве такие дороги, Андрейко, по которым напрямую ни пеший не пройдет, ни конный не проедет, ни в самобеглой коляске не проскочишь. Где домами дорога загорожена, где заборами. В одном месте пропадёт - в другом появится. А одна дорога в начале своём и вовсе заколодела, да замуравела, вместо дороги деревья да тропы.",
    "id":"145",
    "longanswer":"Имеется в виду Боровское шоссе, в нескольких местах разрезанное новой застройкой. В его начале - парк 50-летия Октября, в парке - огромные человеческие ладони, поставленные несколько лет назад. Большой палец зелёной ладони указывает на огромное яблоко, окруженное скамейками. Ответ: 5",
    "name":"Третий совет Бабы-Яги",
    "quest":"Посреди деревьев зелёная длань высится, большим перстом на яблоко молодильное указывает. Само то яблоко, ты, Андрейко, не трогай, а скамьи, что вокруг яблока поставлены - пересчитай, да число то в бумагу подорожную запиши."
  },
  {
    "answer":"10",
    "description":"В загадке времен застоя говорилось, что она \"начинается на Б, кончается на Ь, любит крепких мужиков, но требует много денег\". Любили и видели её в том числе и многие студенты главного ВУЗа страны.",
    "id":"146",
    "longanswer":"В старой загадке упоминалась Байкало-Амурская магистралЬ. Памятник физику Столетову стоит у физфака МГУ, а у южного торца корпуса физфака не так давно поставлен памятник студентам-стройотрядовцам, которые, в том числе, участвовали в сооружении БАМа. Ответ: 10",
    "name":"Загадка",
    "quest":"Памятник к югу от Столетова. Сумма цифр после названия любительницы мужиков и денег на постаменте памятника."
  },
  {
    "answer":"6",
    "description":"Из двух одноименных станций выберите ту, что была закрыта для пассажиров раньше, и расположена от объекта, по которому названа, дальше.",
    "id":"147",
    "longanswer":"Загаданы железнодорожная станция \"Воробьевы Горы\" и станция метрополитена \"Воробьевы Горы\". Обе они в своё время были закрыты для пассажиров - вначале станция на Малом кольце, потом - станция метро. Однако здание станции железной дороги цело, как и роскошный металлический мост от него к бывшей пассажирской платформе. Ответ: 6",
    "name":"Загадка",
    "quest":"Кол-во столбов для фонарей на мосту, предназначавшемуся для выхода пассажиров на платформу."
  },
  {
    "answer":"2",
    "description":"Эта улица считается самым тёплым местом города. Место, где в действительности были получены эти данные, можно увидеть с моста у конца этой улицы.",
    "id":"148",
    "longanswer":"Загадан достаточно известный факт - самое теплое место Москвы - Балчуг. Обычно считается, что это улица Балчуг, однако на самом деле рекорд температуры был замерен на метеостанции \"Балчуг\", расположенной на Овчинниковской набережной Водоотводного канала. Ответ: 2",
    "name":"Загадка",
    "quest":"На месте, где был установлен рекорд, найдите будку с надписью ЦГМС-Р на табличке. Кол-во нулей в телефонных номерах на табличке."
  },
  {
    "answer":"1992",
    "description":"Дам я тебе, Андрейко, карту старинную. Где круг на карте нарисован, найдешь ты крест каменный. На камне у подножия того креста год высечен.",
    "id":"149",
    "image":"http://img.runcity.org/img/routes/msk2010-cp149-med.jpg",
    "longanswer":"На старой карте, которую европейские картографы ориентировали на запад, помещен участок города Москвы между Москвой-рекой и Яузой, видна стена Белого города, идущая по линии Бульварного кольца. Церковь в кружке - на стрелке Николоямской и Яузской. Церковь сломана в 1930-х, сейчас тут стоит закладной крест памятнику Дмитрию Донскому, поставленный еще в начале 1990-х. Ответ: 1992",
    "name":"Четвертый совет Бабы-Яги",
    "quest":"Хочешь Бибигонище одолеть - год тот найди, да в бумагу подорожную запиши."
  },
  {
    "answer":"подпись",
    "description":"Беседка напротив д. 65 по ул. Удальцова",
    "id":"150",
    "lat":"55.6798045",
    "lon":"37.5015092",
    "name":"Парк 50-летия Октября",
    "quest":"Подпись судьи"
  },
  {
    "answer":"кузнецы",
    "description":"Прорезная табличка на шпиле над крыльцом",
    "id":"151",
    "lat":"55.7586656",
    "lon":"37.6017916",
    "name":"Леонтьевский пер., д. 7",
    "quest":"Профессия изображенных на табличке"
  },
  {
    "answer":"3",
    "description":"Сквер со скульптурами перед д. 11",
    "history":"Скульптуры в сквере перед домом 11 по Сивцеву Вражку появились не так давно. Несмотря на странные формы некоторых из них, они несомненно оживили и украсили начало переулка. Их автор - известный скульптор Александр Николаевич Бурганов, многие годы возглавляющий кафедру монументальной и декоративной скульптуры МХПИ им. Строганова, создатель целого ряда московских памятников, например - скульптурной группы \"Пушкин и Натали\" у Никитских ворот. Творческая мастерская Бурганова, расположенная в соседнем Большом Афанасьевском переулке, не так давно получила официальный статус государственного музея \"Дом Бурганова\".",
    "id":"152",
    "lat":"55.7475441",
    "lon":"37.5958586",
    "name":"Пер. Сивцев Вражек",
    "quest":"Кол-во лошадиных морд"
  },
  {
    "answer":"ART ELL",
    "description":"Стена, украшенная битой посудой",
    "id":"153",
    "lat":"55.7597281",
    "lon":"37.5973284",
    "name":"Малая Бронная ул., д. 4",
    "quest":"Надпись на металлической двери"
  },
  {
    "answer":"знак",
    "description":"Основание столба у забора строительной площадки",
    "history":"Хитровская площадь была создана в 1824-1825 годах на месте выгоревших в 1812 году построек и получила название по фамилии своего создателя - генерал-майора Н. З. Хитрово. Первоначально площадь была известна своим рынком, где торговали мясом и зеленью. Однако затем площадь стала местом сбора людей, пришедших в Москву в поисках работы, и к концу XIX века превратилась в одно из самых злачных мест города. Окрестности \"Хитровки\" заполонили ночлежки и кабаки, а само название стало нарицательным. Разогнать притоны \"Хитровки\" удалось только в 1924 году. Взамен рынка на месте площади соорудили школьное здание. Сейчас оно снесено. Планируется строительство на его месте офисного здания, однако защитники старины справедливо опасаются, что новое строительство окончательно изуродует застройку окрестных кварталов, и настаивают на восстановлении площади в тех формах, которые предполагались при её создании. Будущее Хитровки окончательно еще не определено.",
    "id":"155",
    "lat":"55.7533589",
    "lon":"37.643913",
    "name":"Хитровский пер., д. 3",
    "quest":"Знак"
  },
  {
    "answer":"12",
    "description":"Подпорная стенка во дворе дома",
    "id":"156",
    "lat":"55.75418",
    "lon":"37.6559186",
    "name":"Ул. Земляной Вал, д. 42/20",
    "quest":"Кол-во глухих арок"
  },
  {
    "answer":"8",
    "description":"Арка во двор дома",
    "history":"Этот многоэтажный дом на углу Земляного Вала и переулка Обуха построен в 1939 году. Еще одно крыло было пристроено к дому в 1954 году. Проект здания разработали архитекторы Александр Федорович Хряков и Зоя Осиповна Брод. Это одна из первых работ Хрякова в Москве. В послевоенные годы он участвовал в проектировании и строительстве комплекса зданий МГУ на Воробьевых Горах. Достопримечательностью дома 48 является огромная арка высотой в семь этажей, прорезающая дом почти до самого верха. Эта арка считается самой высокой среди арок в московских домах.",
    "id":"157",
    "lat":"55.7521211",
    "lon":"37.6556611",
    "name":"Ул. Земляной Вал, д. 48-А",
    "quest":"Кол-во застекленных оконных проемов внутри арки"
  },
  {
    "answer":"2",
    "description":"Изразцы на стене со стороны 5-го Котельнического пер.",
    "history":"Церковь Успения в Гончарах построена в 1654 году. В 1702 году к ней пристроили трапезную, еще позже соорудили церковную колокольню. Здание выделяется своим декоративным убранством - в конце XVII века в Гончарной Слободе, приходским храмом которой она являлась, процветало \"ценинное дело\" - изготовление изразцов. Северная стена церковной трапезной, выходящая в переулок, является своеобразной выставкой лучших образцов изразцов, производившихся в те годы. Интересны и изразцовые фигуры евангелистов на барабане южного придела церкви. В годы советской власти эта церковь - одна из немногих в центре Москвы - избежала закрытия. С 1948 года она имеет статус подворья Болгарской Православной Церкви.",
    "id":"158",
    "lat":"55.7422358",
    "lon":"37.6503181",
    "name":"Гончарная ул., д. 29",
    "quest":"Кол-во изображений херувимов"
  },
  {
    "description":"Татары",
    "id":"160",
    "lat":"55.7158224",
    "lon":"37.4711251",
    "name":"Мыс на правом берегу р. Сетунь напротив д. 5 по Нежинской ул.",
    "quest":"Стикер"
  },
  {
    "answer":"паровоз (поезд)",
    "description":"Плакат у входа в \"Народную галерею\"",
    "id":"161",
    "lat":"55.759215",
    "lon":"37.6409841",
    "name":"Потаповский пер., д. 16/5 стр. 3",
    "quest":"Картинка над фотографией пары сапог, вид транспортного средства"
  },
  {
    "answer":"2589",
    "description":"Кафельная плитка слева от входа в булочную",
    "id":"162",
    "lat":"55.7584423",
    "lon":"37.6395464",
    "name":"Ул. Покровка, д. 1",
    "quest":"Телефонный номер"
  },
  {
    "answer":"1868",
    "description":"Памятные доски на здании",
    "id":"163",
    "lat":"55.7628128",
    "lon":"37.6307273",
    "name":"Милютинский пер., д. 8 стр. 1",
    "quest":"Самый поздний год"
  },
  {
    "answer":"НКИД, НКВТ",
    "description":"Памятник Воровскому",
    "id":"164",
    "lat":"55.7624506",
    "lon":"37.6270258",
    "name":"Пл. Воровского",
    "quest":"Аббревиатуры названий наркоматов на постаменте"
  },
  {
    "answer":"воздушные шары",
    "description":"Граффити с улитками на стене дома",
    "id":"165",
    "lat":"55.7547596",
    "lon":"37.6372182",
    "name":"Большой Спасоглинищевский пер., д. 9/1 стр. 22",
    "quest":"Вид изображенных летательных аппаратов"
  },
  {
    "answer":"5",
    "description":"Быв. вокзал станции \"Воробьевы Горы\". Металлический мост от вокзала к путям.",
    "history":"Московская окружная железная дорога была построена вокруг Москвы в 1903-1908 годах. Среди множества её станций особо выделяется станция \"Воробьевы Горы\". Хотя пассажирского движения по кольцу нет с 1930-х годов, а большинство станционных построек разобрано, уцелело основное здание - старый вокзал, выстроенный по проекту А. Н. Померанцева. Интересно, что пути дороги проходят по насыпи, а потому выход на платформы сделан со второго этажа вокзального здания. Здесь до наших дней уцелел арочный металлический пешеходный мостик 1900-х годов.",
    "id":"166",
    "lat":"55.7202581",
    "lon":"37.5631034",
    "name":"Ул. Хамовнический Вал, напротив д. 32",
    "quest":"Кол-во колонн с целыми фонарями"
  },
  {
    "description":"Балконы на торце дома, обращенном к д. 26",
    "id":"169",
    "lat":"55.7240045",
    "lon":"37.5875115",
    "name":"Фрунзенская наб., д. 32",
    "quest":"Кол-во застекленных балконов"
  },
  {
    "description":"Склон берега над Воробьевской наб., 300 м западнее ст. м. \"Воробьевы Горы\".",
    "id":"170",
    "lat":"55.709531",
    "lon":"37.55245",
    "name":"Воробьевы Горы",
    "quest":"Подпись судьи"
  },
  {
    "answer":"волшебство",
    "description":"Голубятня за домом, надпись на двери",
    "id":"172",
    "lat":"55.7245241",
    "lon":"37.5598204",
    "name":"Учебный пер., д. 3",
    "quest":"Кто здесь живёт?"
  },
  {
    "answer":"Налич",
    "description":"Памятник \"Лента Мебиуса\"",
    "id":"174",
    "lat":"55.7279861",
    "lon":"37.5841641",
    "name":"Угол Комсомольского пр-та и 1-й Фрунзенской ул.",
    "quest":"Фамилия, дважды написанная на пъедестале"
  },
  {
    "answer":"6",
    "description":"Деревянная пушка рядом с усадебными постройками",
    "history":"Усадьба Воронцово у Калужской дороги существовала уже в XVIII веке. Она относится к числу небольших и малоизвестных \"подмосковных\". Основные усадебные постройки - дом с флигелями, парные башни у въездных ворот - были сооружены в 1770-1780-х годах, когда усадьба принадлежала князьям Репниным. В северо-восточной части усадьбы стоит небольшая Троицкая церковь. Любопытно, что основной объем церковного здания - бывшая садовая башня, переделанная в церковь в 1807 году. До 1980-х годов усадебные строения занимали производственные помещения. В последние годы ведется их реставрация, часть построек, в том числе и главный дом, сгоревший в 1920-х, строятся заново, благоустроен усадебный парк.",
    "id":"175",
    "lat":"55.665792",
    "lon":"37.533036",
    "name":"Воронцовский парк",
    "quest":"Кол-во деревянных солдат вокруг пушки"
  },
  {
    "answer":"56, 57, 58, 59, 60",
    "description":"Жилой дом",
    "id":"176",
    "lat":"55.6853",
    "lon":"37.534",
    "name":"Ул. Строителей, д. 5 корп. 1",
    "quest":"Какие квартиры находятся одновременно во 2-ом и 3-ем подъездах?"
  },
  {
    "answer":"Наровчатов",
    "description":"Мемориальная доска на доме",
    "id":"177",
    "lat":"55.68725",
    "lon":"37.53586",
    "name":"Ул. Строителей, д. 4 корп. 1",
    "quest":"Фамилия Сергея Сергеевича"
  },
  {
    "answer":"VOLVO",
    "description":"Сетуньский стан, автомобиль на постаменте рядом с вышкой",
    "history":"Местность в устье реки Сетуни была заселена издревле. В XV-XVI веках здесь существовало сельцо Воишевское, позже уничтоженное разбойниками. В конце XIX века тут выстроили загородную дачу Николаевского сиротского института, находившегося в Москве. Летом сюда перебирались из центра города воспитанницы института. Сейчас наибольшей известностью пользуется историко-культурный комплекс \"Сетуньский стан\", обустроенный в 1990-х в пойме Сетуни на основе тренировочной базы каскадеров. Здесь сооружен стилизованный под Древнюю Русь городок, проводятся экскурсии, демонстрируются бои на мечах и различные каскадерские трюки.",
    "id":"178",
    "lat":"55.730923",
    "lon":"37.536737",
    "name":"2-й Сетуньский пр.",
    "quest":"Название фирмы на правом переднем колесном колпаке"
  },
  {
    "description":"Беседка перед домом",
    "id":"180",
    "lat":"55.7291642",
    "lon":"37.5725126",
    "name":"Ул. Усачева, д. 6",
    "quest":"Подпись судьи"
  },
  {
    "answer":"S, O, N, W",
    "description":"Глобус на вершине башенки",
    "id":"181",
    "lat":"55.727844",
    "lon":"37.536173",
    "name":"Воробьевское ш., д. 4А",
    "quest":"Буквы на глобусе"
  },
  {
    "answer":"4",
    "description":"Мемориальная доска, посвященная режиссеру",
    "history":"Многоэтажный дом начала 1970-х годов на улице Пырьева украшает мемориальная доска, установленная в 2000 году. Она напоминает о том, что в 1973-1982 годах здесь жил известный кинорежиссер и сценарист Андрей Арсеньевич Тарковский. В годы, которые он провёл в мосфильмовском доме на Пырьева, Тарковским были сняты фильмы \"Зеркало\" и \"Сталкер\". В 1982 году Тарковский уехал в Италию и более уже не вернулся в СССР.",
    "id":"182",
    "lat":"55.725865",
    "lon":"37.528798",
    "name":"Ул. Пырьева, д. 4 корп 2",
    "quest":"Кол-во букв \"Р\""
  },
  {
    "description":"Старый Рублевский мост через р. Сетунь",
    "id":"183",
    "lat":"55.72254",
    "lon":"37.504842",
    "name":"Ул. Улофа Пальме",
    "quest":"Знак"
  },
  {
    "answer":"сокровищ",
    "description":"Рисунок на торцевой стене дома",
    "id":"184",
    "lat":"55.718602",
    "lon":"37.511363",
    "name":"Ул. Улофа Пальме, д. 3",
    "quest":"Второе слово в названии документа, находящегося в клешнях у ракообразного"
  },
  {
    "answer":"PAL",
    "description":"Памятник",
    "id":"186",
    "lat":"55.706803",
    "lon":"37.513612",
    "name":"Сквер между Мичуринским пр-том и ул. Дружбы",
    "quest":"Подпись скульптора. Самое короткое слово"
  },
  {
    "answer":"знаки (4 шт.)",
    "description":"Велотрасса, см. схему",
    "id":"188",
    "image":"http://img.runcity.org/img/routes/msk2010-cp188-med.jpg",
    "lat":"55.767136",
    "lon":"37.420084",
    "name":"Крылатская ул., д.17",
    "quest":"Проехать по линии, отмеченной на схеме, собрать 4 знака"
  },
  {
    "answer":"3",
    "description":"Забор вдоль Мосфильмовской улицы",
    "id":"189",
    "lat":"55.722495",
    "lon":"37.534441",
    "name":"Мосфильмовская ул., д. 1",
    "quest":"Кол-во изображенных ваз"
  },
  {
    "description":"Сквер перед домом",
    "id":"190",
    "lat":"55.766613",
    "lon":"37.579933",
    "name":"Большая Грузинская ул., д. 22",
    "quest":"Подпись судьи"
  },
  {
    "answer":"11",
    "description":"Сквер напротив дома, памятник солдатам-афганцам",
    "id":"191",
    "lat":"55.6809961",
    "lon":"37.5574923",
    "name":"Нахимовский пр-т, д. 52/27",
    "quest":"Кол-во букв \"О\" в надписи"
  },
  {
    "answer":"УГ",
    "description":"Красно-белый плакат в арке",
    "id":"193",
    "lat":"55.7709005",
    "lon":"37.6369715",
    "name":"Ананьевский пер., д. 4/2 стр. 1",
    "quest":"Двухбуквенная аббревиатура"
  },
  {
    "answer":"1909 (c 13:00 - задание заклеено)",
    "description":"Плакаты с изображениями пожарных машин",
    "history":"Рыбников переулок - один из множества параллельных переулков, вытянувшихся в обе стороны от Сретенки. Своё название он получил от домовладельца Андрея Рыбникова - \"артиллерии зелейного ученика\" - специалиста по изготовлению пороха. Памятная доска на здании пожарной части в переулке установлена в 2007 году в память известного пожарного, генерал-майора Владимира Михайловича Максимчука. В мае 1986 года Максимчук - тогда еще подполковник - руководил сводным отрядом пожарных на Чернобыльской АЭС, а в последние годы жизни возглавлял управление пожарной охраны города Москвы.",
    "id":"194",
    "lat":"55.7673518",
    "lon":"37.6334417",
    "name":"Рыбников пер., д. 5",
    "quest":"Год под изображением конной упряжки"
  },
  {
    "answer":"15",
    "description":"Подъезд со стороны переулка",
    "id":"195",
    "lat":"55.767382",
    "lon":"37.6257384",
    "name":"Колокольников пер., д. 10",
    "quest":"Кол-во металлических табличек для номеров квартир"
  },
  {
    "answer":"6",
    "description":"Картина на фасаде здания в 100 м от Екатерининского пруда",
    "history":"Екатерининский пруд в Нескучном саду был назван в честь императрицы Екатерины II. Этот небольшой пруд причудливой формы с островком посередине расположен в центральной части парка, чуть выше по течению, чем основные постройки усадьбы. К северу от пруда стоит так называемый \"Летний домик\", сооруженный в 1790-х годах, одновременно с реконструкцией этой части сада, по указанию его владельца, графа Алексея Григорьевича Орлова. Сейчас в \"Летнем домике\" помещена библиотека.",
    "id":"196",
    "lat":"55.7192791",
    "lon":"37.5890136",
    "name":"Ул. Крымский Вал, д. 9 стр. 55",
    "quest":"Кол-во людей в пилотках"
  },
  {
    "answer":"350",
    "description":"Робот у крыльца",
    "id":"197",
    "lat":"55.7380985",
    "lon":"37.5725448",
    "name":"1-й Тружеников пер., д. 12",
    "quest":"Цифры после букв РР внутри шлема"
  },
  {
    "answer":"7",
    "description":"Палаты Хамовного двора",
    "history":"Двухэтажные палаты на улице Льва Толстого - одно из старейших гражданских зданий в этой части города, и редчайший образец палат XVII века вне Садового кольца. Они были сооружены в 1680-1690-х годах в центре дворцовой Хамовной слободы, жители которой занимались ткацким промыслом. В XVIII-XIX веках палаты были сильно перестроены и выявлены как старинный памятник только в 1950-х. В 1970-1980-х годах палаты отреставрировали в первоначальных формах.",
    "id":"199",
    "lat":"55.732502",
    "lon":"37.589302",
    "name":"Ул. Льва Толстого, д. 10 стр. 2",
    "quest":"Кол-во окон с металлическими ставнями"
  },
  {
    "description":"Посреди большой речной петли, между полем и парком с прудом. Дом 2 на улице, проходящей с севера от парка, вход в музей.",
    "id":"200",
    "lat":"55.7310975",
    "lon":"37.5777054",
    "name":"Загадка",
    "quest":"Подпись судьи"
  },
  {
    "answer":"сова, филин",
    "description":"Двор со статуями медведей",
    "id":"201",
    "lat":"55.7305779",
    "lon":"37.5915349",
    "name":"Комсомольский пр-т, д. 9А",
    "quest":"Птица на столбе, перекладиной соединенном с жёлтым медведем"
  },
  {
    "answer":"2",
    "description":"Ворота во двор старообрядческой церкви",
    "history":"Старообрядческая Покровская церковь в Турчаниновом переулке - одна из первых в Москве построек неорусского стиля. Здание церкви, сочетающие черты модерна и средневекового псковского зодчества, выстроено в 1907-1911 годах по проекту архитекторов Владимира Дмитриевича Адамовича и Владимира Морицевича Маята. Средства на строительство церкви выделил известный предприниматель Степан Павлович Рябушинский, владелец знаменитого шехтелевского особняка на Малой Никитской улице (сейчас в этом здании дом-музей Горького). В 1932 году церковь была закрыта, занята ВНИИ \"Биотехника\" и возвращена старообрядческой общине только в 1994 году.",
    "id":"202",
    "lat":"55.7366308",
    "lon":"37.5977898",
    "name":"Турчанинов пер., д. 4",
    "quest":"Кол-во львиных морд на полотнищах ворот"
  },
  {
    "answer":"знак",
    "description":"Кирпичный короб за домом",
    "id":"203",
    "lat":"55.7396387",
    "lon":"37.5979829",
    "name":"3-й Зачатьевский пер., д. 3",
    "quest":"Знак"
  },
  {
    "answer":"знак",
    "description":"Лестница во дворе дома",
    "id":"204",
    "lat":"55.7672612",
    "lon":"37.5739396",
    "name":"Ул. Климашкина, д. 9",
    "quest":"Знак"
  },
  {
    "answer":"12",
    "description":"Колесо за забором",
    "id":"205",
    "lat":"55.7662352",
    "lon":"37.5766003",
    "name":"Большая Грузинская ул., д. 15 стр. 2",
    "quest":"Кол-во спиц"
  },
  {
    "answer":"1",
    "description":"Жилой дом",
    "id":"207",
    "lat":"55.7711419",
    "lon":"37.5900757",
    "name":"2-я Брестская ул., д. 19/18",
    "quest":"Кол-во львиных масок"
  },
  {
    "answer":"письма мастеру",
    "description":"Внутренний двор",
    "history":"Дом 10 по Большой Садовой сейчас больше всего известно булгаковским музеем. Это здание выстроили в 1902-1903 году как доходный дом промышленника И. Д. Пигита, владельца табачной фабрики \"Дукат\". В предреволюционные годы в этом доме жило немало деятелей искусства. Но наибольшую известность дому дал Михаил Афанасьевич Булгаков, поселившийся тут в коммунальной квартире в 1921 году, и проживший здесь три года. Считается, что именно дом 10 и булгаковская коммуналка в нём послужили прообразом дома 302бис и \"нехорошей\" 50-й квартиры, в которых разворачивались многие события романа \"Мастер и Маргарита\".",
    "id":"208",
    "lat":"55.7670923",
    "lon":"37.5935626",
    "name":"Большая Садовая ул., д. 10",
    "quest":"Надпись на почтовом ящике под совой"
  },
  {
    "answer":"9",
    "description":"Росписи вокруг дверей подъездов",
    "history":"Многоэтажный дом 5-7 по Глинищевскому переулку построили в 1938 году для артистов театра МХАТ по проекту В. Н. Владимирова. Это характерный для зодчества того времени 8-этажный дом с 12-этажной башней, украшенный рельефами и колоннами. До 1930-х годов на месте этого дома стояла церковь Алексия митрополита, что на Глинищах, сооруженная в конце XVII века дьяком Иваном Алферьевым. Помимо прочего, Алексеевская церковь была интересна сохранявшейся с XVII века изразцовой черепицей на луковичных куполах. Среди множества мемориальных досок, повешенных в память о живших в доме артистов, есть и доска в память этого утраченного храма.",
    "id":"209",
    "lat":"55.7635975",
    "lon":"37.6109755",
    "name":"Глинищевский пер., д. 5/7",
    "quest":"Кол-во медальонов с портретами"
  },
  {
    "answer":"4",
    "description":"Торец здания, обращенный в Богословский пер.",
    "id":"211",
    "lat":"55.7621126",
    "lon":"37.6016843",
    "name":"Тверской б-р, д. 23",
    "quest":"Кол-во нарисованных тёмных деревьев на светлом фоне"
  },
  {
    "answer":"1948",
    "description":"Лепнина на фасаде здания",
    "id":"212",
    "lat":"55.7651246",
    "lon":"37.5980151",
    "name":"Трехпрудный пер., д. 8",
    "quest":"Дата"
  },
  {
    "answer":"TARASSOF",
    "description":"Фасад по Спиридоновке",
    "id":"213",
    "lat":"55.7621971",
    "lon":"37.5907195",
    "name":"Большой Патриарший пер., д. 1",
    "quest":"Фамилия, написанная латинскими буквами"
  },
  {
    "answer":"Москва, Яуза",
    "description":"Карта города на стене",
    "history":"Краснокирпичный дом 7 в Гранатном переулке, украшенный белокаменными деталями - хороший образец московской неоготики. Этот особняк соорудили в 1896 году по проекту архитектора Адольфа Вильгельма Эрихсона для потомственной почетной гражданки Анны-Луизы Леман. Среди множества других построек Эрихсона - телефонная станция в Милютинском переулке, Щукинский музей на Малой Грузинской (ныне биологический музей им. Тимирязева), рестораны \"Яр\" и \"Прага\". В 1919 году в этом здании помещался главный штаб Реввоенсовета, а с конца 1930-х годов здесь находится Центральный дом архитектора.",
    "id":"214",
    "lat":"55.7595772",
    "lon":"37.5903547",
    "name":"Гранатный пер., д. 7",
    "quest":"Названия изображенных на карте рек"
  },
  {
    "answer":"конфекты",
    "description":"Картина на торцевой стене",
    "history":"Здание на углу Калашного и Кисловского переулков известно как \"Дом Моссельпрома\". В 1990-х годах были восстановлены огромные рекламные картины, украшавшие это здание в 1920-х годах и выполненные при участии В. С. Маяковского. История участка, на котором стоит дом, не менее интересна. В XVII-XVIII веках здесь находилась каменная церковь Иоанна Милостивого. После пожара 1812 года церковь не стали восстанавливать, а разобрали, застроив её участок частными домами. Постройка многоэтажного здания на углу переулков была начата ещё до революции. Но из-за спешки и халтуры в 1913 году недостроенный дом обрушился. Первая Мировая война и революция окончательно приостановили строительство, завершенное только в 1925 году по новому проекту. \"Дом Моссельпрома\" стал одним из первых высотных домов советской Москвы и даже получил прозвание \"первого советского небоскреба\".",
    "id":"215",
    "lat":"55.7539385",
    "lon":"37.602843",
    "name":"Нижний Кисловский пер., д. 10",
    "quest":"Название продукта, не соответствующее современной грамматике"
  },
  {
    "answer":"1901",
    "description":"Керамические панно под карнизом",
    "history":"Все дома на перекрестке Хлебного и Малого Ржевского переулков были сооружены в начале ХХ века. Среди них особенно выделяется дом 6 - хороший образец московского модерна, украшенный майоликами. Он выстроен известным московским архитектором Сергеем Устиновичем Соловьевым как собственный дом. По проектам Соловьева в Москве возведено немало общественных зданий, отличающихся гармоничностью пропорций и проработанностью деталей. В их числе: комплекс Медведниковской (ныне 5-й Градской) больницы на Ленинском проспекте; здание Коммерческого института (ныне \"Плешка\" - экономический университет им. Плеханова) в Стремянном переулке; здание Высших женских курсов на Девичьем поле и другие. С 1920-х годов в доме Соловьева располагается постпредство Грузинской ССР. Посольство Грузии размещено здесь и в наши дни.",
    "id":"217",
    "lat":"55.7558222",
    "lon":"37.59323",
    "name":"Малый Ржевский пер., д. 6",
    "quest":"Год арабскими цифрами"
  },
  {
    "answer":"2",
    "description":"Доска на фасаде",
    "id":"218",
    "lat":"55.7414869",
    "lon":"37.6418102",
    "name":"Космодамианская наб., д. 26/55 стр. 2",
    "quest":"Число"
  },
  {
    "answer":"URSS",
    "description":"Памятная доска на южном фасаде",
    "id":"219",
    "lat":"55.7586777",
    "lon":"37.5807202",
    "name":"Кудринская пл., д. 1",
    "quest":"Надпись на левом крыле самолёта"
  },
  {
    "answer":"задание закрашено",
    "description":"Картины в арке",
    "id":"221",
    "lat":"55.7504546",
    "lon":"37.5783169",
    "name":"Панфиловский пер., д. 1",
    "quest":"Названия городов, постройки-символы которых нарисованы"
  },
  {
    "answer":"Варяг",
    "description":"Памятная доска, помещенная под мачтой с андреевским флагом",
    "id":"222",
    "lat":"55.7354589",
    "lon":"37.6438057",
    "name":"Садовническая ул., вл. 77",
    "quest":"Название корабля"
  },
  {
    "answer":"10",
    "description":"Сквер над набережной напротив дома, дерево с красными буквами ПГ",
    "id":"223",
    "lat":"55.7426767",
    "lon":"37.5745511",
    "name":"Ростовская наб., д. 5",
    "quest":"Цифры под буквами"
  },
  {
    "answer":"Цилиндр",
    "description":"Статуя в парке слева от дома",
    "id":"224",
    "lat":"55.7407682",
    "lon":"37.5821471",
    "name":"1-й Неопалимовский пер., д. 4",
    "quest":"Головной убор"
  },
  {
    "answer":"3",
    "description":"Окна музыкальной школы №55",
    "id":"225",
    "lat":"55.6957769",
    "lon":"37.5513554",
    "name":"Университетский пр-т, д. 5",
    "quest":"Кол-во смайликов в очках"
  },
  {
    "answer":"2",
    "description":"Плакат \"Экологические тропы\"",
    "id":"227",
    "lat":"55.7115917",
    "lon":"37.546699",
    "name":"Воробьевская наб., Причал \"Воробьевы Горы\"",
    "quest":"Кол-во изображений рыб на плакате"
  },
  {
    "answer":"2008",
    "description":"Граффити по сторонам ворот со стороны Мароновского пер.",
    "id":"228",
    "lat":"55.7322634",
    "lon":"37.6090336",
    "name":"2-й Бабьегородский пер., вл. 29",
    "quest":"Цифры на номере автомашины"
  },
  {
    "answer":"кафе-клуб",
    "description":"Зонтик на углу здания.",
    "history":"Голутвинские переулки получили своё название по Голутвинский слободе, существовавшей уже в XVI веке. В 1-м Голутвинском переулке сохранилось здание приходской Никольской церкви, сооруженной в 1688-1692 годах. Краснокирпичные корпуса, протянувшиеся вдоль всего 4-го Голутвинского переулка принадлежали в начале ХХ века ткацкой фабрике \"Товарищества Московской Голутвинской мануфактуры\", разросшейся из небольшой фабрики, основанной в 1846 году купцами Рябушинскими. Главный корпус с мануфактуры выстроили в 1910-х годах. После революции фабрика была переименована в \"Красные текстильщики\" и действовала до 1990-х годов. В настоящее время в реконструированных фабричных корпусах помещен бизнес-центр \"Голутвинский\".",
    "id":"229",
    "lat":"55.7392401",
    "lon":"37.6135826",
    "name":"Угол 1-го Голутвинского пер. и 4-го Голутвинского пер.",
    "quest":"Надпись на зонтике."
  },
  {
    "answer":"грам",
    "description":"Граффити на ТП к северо-западу",
    "id":"232",
    "lat":"55.7630844",
    "lon":"37.4795687",
    "name":"Филёвский б-р, д. 41",
    "quest":"Слово на карандаше"
  },
  {
    "answer":"10",
    "description":"Детская площадка напротив д. 1 по ул. Артамонова",
    "id":"233",
    "lat":"55.718987",
    "lon":"37.462414",
    "name":"Кременчугская ул.",
    "quest":"Кол-во колёс у паровоза"
  },
  {
    "answer":"995-99-99",
    "description":"Предупредительные таблички у пруда",
    "id":"236",
    "lat":"55.687577",
    "lon":"37.437657",
    "name":"Угол Очаковского ш. и ул. Генерала Дорохова",
    "quest":"Номер телефона с наибольшей суммой цифр"
  },
  {
    "answer":"5",
    "description":"Мозаика над крыльцом",
    "history":"Дом 8 в Глазовском переулке сооружен в 1898-1899 годах как собственный особняк одним из лучших мастеров московского модерна - Львом Николаевичем Кекушевым. Позже Кекушев продал дом промышленнику О. Листу. У Листа последнего его купила Наталья Константиновна Кусевицкая - дочь московских купцов-чаеторговцев Ушковых, вложившая значительную часть своего состояния в поддержку начинаний собственного мужа, дирижера и контрабасиста Сергея Александровича Кусевицкого. Кусевицкими было создано \"Российское музыкальное издательство\", организован собственный оркестр, в их особняке в Глазовском бывали многие знаменитые композиторы.",
    "id":"237",
    "lat":"55.7440536",
    "lon":"37.5863421",
    "name":"Глазовский пер., д. 8",
    "quest":"Кол-во представителей водной фауны"
  },
  {
    "answer":"1997",
    "description":"Доска над средней входной дверью",
    "id":"238",
    "lat":"55.742266",
    "lon":"37.5931442",
    "name":"Чистый пер., д. 3",
    "quest":"Год на доске"
  },
  {
    "answer":"600, 951",
    "description":"Сквер перед домом. Будка с табличкой \"Пост\"",
    "id":"239",
    "lat":"55.745503",
    "lon":"37.6299977",
    "name":"Средний Овчинниковский пер., д. 1 стр. 1",
    "quest":"Трехзначные цифры на табличке"
  },
  {
    "answer":"лиса",
    "description":"Граффити на постройке к востоку от дома",
    "history":"Своё название Казарменный переулок получил от Покровских казарм, массивное здание которых возвышается на углу переулка с Покровским бульваром. Стоящее во дворе домовладения 10 строение 3 - одно из старейших в этой части города. Этот дом с мезонином сооружен вскоре после пожара 1812 года доктором медицины И. А. Воскресенским. Два кирпичных корпуса по линии Казарменного переулка, отгородившие старый дом от улицы, сооружены в последней четверти XIX века.",
    "id":"241",
    "lat":"55.7564802",
    "lon":"37.651906",
    "name":"Казарменный пер., д. 10 стр. 3",
    "quest":"Животное рядом с бочкой радиоактивных отходов"
  },
  {
    "answer":"за уважение",
    "description":"Металлический гараж во дворе дома, слева от ворот",
    "id":"242",
    "lat":"55.7592029",
    "lon":"37.6559186",
    "name":"Яковоапостольский пер., д. 15",
    "quest":"За что говорят спасибо?"
  },
  {
    "answer":"50",
    "description":"2-й подъезд",
    "id":"244",
    "lat":"55.7642856",
    "lon":"37.6457691",
    "name":"Ул. Чаплыгина, д. 1-А",
    "quest":"Максимальный номер квартиры на штукатурной табличке"
  },
  {
    "answer":"чудес",
    "description":"Забор с изображением аиста во дворе дома",
    "id":"245",
    "lat":"55.7716187",
    "lon":"37.6134753",
    "name":"Малый Каретный пер., д. 7",
    "quest":"Надпись со словом \"Театр\" справа от аиста. Второе слово"
  },
  {
    "answer":"1",
    "description":"Нарисованное окно с видом на море",
    "id":"246",
    "lat":"55.7693495",
    "lon":"37.603637",
    "name":"Старопименовский пер., д. 14 стр. 4",
    "quest":"Кол-во изображенных людей, смотрящих в окно"
  },
  {
    "answer":"Страстная",
    "description":"Плакаты на заборе справа от ворот",
    "id":"247",
    "lat":"55.7339427",
    "lon":"37.6229221",
    "name":"Щетининский пер., д. 10 стр. 1",
    "quest":"Название площади на ближайшем к воротам плакате"
  },
  {
    "answer":"диван",
    "description":"Рельеф на фасаде",
    "id":"248",
    "lat":"55.7323147",
    "lon":"37.6283509",
    "name":"1-й Монетчиковский пер., д. 5",
    "quest":"Предмет мебели"
  },
  {
    "answer":"Динес",
    "description":"Памятник Пушкину",
    "id":"251",
    "lat":"55.7499534",
    "lon":"37.5877476",
    "name":"Спасопесковская пл.",
    "quest":"Фамилия у левой пятки"
  },
  {
    "answer":"1926",
    "description":"Памятная доска на фасаде",
    "id":"252",
    "lat":"55.7354771",
    "lon":"37.6350725",
    "name":"Ул. Бахрушина, д. 12",
    "quest":"Самая поздняя из дат"
  },
  {
    "answer":"2",
    "description":"Скульптура во дворе дома",
    "history":"Дом 17 по Мясницкой выстроен в 1877 году по проекту В. А. Косова. Вскоре это здание купил известный благотворитель, купец Флор Яковлевич Ермаков. На деньги Ермакова в Москве действовали два крупных корпуса богаделен, были открыты техническое училище и несколько ночлежек. После смерти Ермакова дом на Мясницкой был передан Комитету богадельни Ермаковых. Средства, полученные от арендаторов, размещавшихся в здании, шли на поддержку созданных Ермаковым благотворительных заведений. Из внутреннего двора дома 17 хорошо видны ярко-красные многоэтажные корпуса, построенные для преподавателей Училища живописи, ваяния и зодчества.",
    "id":"254",
    "lat":"55.7635733",
    "lon":"37.6350725",
    "name":"Мясницкая ул., д. 17",
    "quest":"Кол-во искусственных голубей"
  },
  {
    "answer":"2",
    "description":"Фасад здания, обращенный в сторону ул. Фотиевой",
    "id":"255",
    "lat":"55.703038",
    "lon":"37.554457",
    "name":"Ул. Косыгина, д. 17 корп. 1",
    "quest":"Кол-во китов на мозаиках"
  },
  {
    "answer":"2",
    "description":"Козырек над подъездом № 1",
    "id":"257",
    "lat":"55.75363",
    "lon":"37.62007",
    "name":"Софийская наб., д. 30 стр. 2",
    "quest":"Кол-во букв \"Ъ\" в надписи на козырьке"
  },
  {
    "answer":"Гремучую",
    "description":"Памятник Осипу Мандельштаму",
    "id":"258",
    "lat":"55.754963",
    "lon":"37.638844",
    "name":"Ул. Забелина",
    "quest":"Слово, написанное ближе всего к носу поэта"
  }
]